mobile_base_sdk/__init__.py
mobile_base_sdk/lidar.py
mobile_base_sdk/mobile_base_sdk.py
mobile_base_sdk-1.0.2.dist-info/LICENSE
mobile_base_sdk-1.0.2.dist-info/METADATA
mobile_base_sdk-1.0.2.dist-info/WHEEL
mobile_base_sdk-1.0.2.dist-info/top_level.txt
mobile_base_sdk-1.0.2.dist-info/RECORD
