Metadata-Version: 2.1
Name: mobile-base-sdk
Version: 1.0.2
Summary: Mobile Base SDK for the Reachy robot.
Home-page: https://github.com/pollen-robotics/mobile-base-sdk
Author: Pollen Robotics
Author-email: contact@pollen-robotics.com
Provides-Extra: doc
License-File: LICENSE
